SARIAD/__init__.py
SARIAD/main.py
SARIAD/config/__init__.py
SARIAD/config/config.py
SARIAD/datasets/__init__.py
SARIAD/datasets/datamodules/image/hrsid/hrsid.py
SARIAD/datasets/datamodules/image/mstar/mstar.py
SARIAD/datasets/datamodules/image/mstar/mstar_importer.py
SARIAD/datasets/datamodules/image/sample_public/sample_public.py
SARIAD/datasets/datamodules/image/sardet/sardet.py
SARIAD/datasets/datamodules/image/ssdd/ssdd.py
SARIAD/models/anomalib_models.py
SARIAD/models/autoencoder.py
SARIAD/models/transformer.py
SARIAD/models/image/MFSA/SARDet_100K/MSFA/image_demo.py
SARIAD/models/image/MFSA/SARDet_100K/MSFA/setup.py
SARIAD/models/image/MFSA/SARDet_100K/MSFA/configs/_base_/default_runtime.py
SARIAD/models/image/MFSA/SARDet_100K/MSFA/configs/_base_/datasets/HRSID.py
SARIAD/models/image/MFSA/SARDet_100K/MSFA/configs/_base_/datasets/SARDet_100k.py
SARIAD/models/image/MFSA/SARDet_100K/MSFA/configs/_base_/datasets/SSDD.py
SARIAD/models/image/MFSA/SARDet_100K/MSFA/configs/_base_/datasets/dior.py
SARIAD/models/image/MFSA/SARDet_100K/MSFA/configs/_base_/datasets/dota.py
SARIAD/models/image/MFSA/SARDet_100K/MSFA/configs/_base_/models/faster-rcnn_r50_fpn.py
SARIAD/models/image/MFSA/SARDet_100K/MSFA/configs/_base_/models/retinanet_r50_fpn.py
SARIAD/models/image/MFSA/SARDet_100K/MSFA/configs/_base_/schedules/schedule_1x.py
SARIAD/models/image/MFSA/SARDet_100K/MSFA/local_configs/DeonDet/gfl_r50_denodet_sardet.py
SARIAD/models/image/MFSA/SARDet_100K/MSFA/local_configs/HRSID/hrsid_MSSM_frcnn_van_b_sar_wavelet.py
SARIAD/models/image/MFSA/SARDet_100K/MSFA/local_configs/HRSID/hrsid_frcnn_van_b_sar_wavelet.py
SARIAD/models/image/MFSA/SARDet_100K/MSFA/local_configs/SARDet/other_backbones/fg_frcnn_IN_sup_sar_convnext_b.py
SARIAD/models/image/MFSA/SARDet_100K/MSFA/local_configs/SARDet/other_backbones/fg_frcnn_IN_sup_sar_convnext_s.py
SARIAD/models/image/MFSA/SARDet_100K/MSFA/local_configs/SARDet/other_backbones/fg_frcnn_IN_sup_sar_convnext_t.py
sariad-0.1.7.dist-info/METADATA
sariad-0.1.7.dist-info/WHEEL
sariad-0.1.7.dist-info/top_level.txt
sariad-0.1.7.dist-info/RECORD
