Metadata-Version: 2.4
Name: SARIAD
Version: 0.1.7
Summary: This package is designed for anomaly detection in Synthetic Aperture Radar (SAR) images, leveraging PyTorch Lightning and models from Anomalib. The package is modular, allowing easy benchmarking and dataset integration.
Author-email: Lucian Chauvin <lucian@tamu.edu>, Joshua Peeples <jpeeples@tamu.edu>
Project-URL: Homepage, https://github.com/Advanced-Vision-and-Learning-Lab/SARIAD
Classifier: Programming Language :: Python :: 3
Classifier: License :: OSI Approved
Classifier: Operating System :: OS Independent
Requires-Python: >=3.13
Requires-Dist: anomalib[loggers]>=2.0.0
Requires-Dist: dotenv>=0.9.9
Requires-Dist: einops>=0.8.1
Requires-Dist: freia>=0.2
Requires-Dist: gdown>=5.2.0
Requires-Dist: kagglehub>=0.3.12
Requires-Dist: kornia>=0.8.1
Requires-Dist: lightning>=2.5.1.post0
Requires-Dist: nlm-torch-new>=0.1.3
Requires-Dist: onnx>=1.18.0
Requires-Dist: open-clip-torch>=2.32.0
Requires-Dist: opencv-python>=4.11.0.86
Requires-Dist: openvino>=2025.1.0
Requires-Dist: pip>=25.1.1
Requires-Dist: pynvim>=0.5.2
Requires-Dist: rarfile>=4.2
Requires-Dist: scikit-image>=0.25.2
Requires-Dist: tifffile>=2025.6.11
Requires-Dist: timm>=1.0.15
Requires-Dist: torch>=2.7.1
Requires-Dist: torchvision>=0.22.1
Requires-Dist: ultralytics>=8.3.159
